probed/__init__.py
probed/cli.py
probed/core.py
probetheus-0.1.0.dist-info/LICENSE
probetheus-0.1.0.dist-info/METADATA
probetheus-0.1.0.dist-info/WHEEL
probetheus-0.1.0.dist-info/entry_points.txt
probetheus-0.1.0.dist-info/top_level.txt
probetheus-0.1.0.dist-info/RECORD
