Metadata-Version: 2.1
Name: probetheus
Version: 0.1.0
Summary: A Python package to design probes against overrepresented sequences in a fastq file.
Author-email: SemiQuant <Jason.Limberis@ucsf.edu>
Classifier: Programming Language :: Python :: 3
Classifier: License :: OSI Approved :: MIT License
Classifier: Operating System :: OS Independent
Classifier: Topic :: Scientific/Engineering :: Bio-Informatics
Requires-Python: >=3.8
License-File: LICENSE
Requires-Dist: biopython>=1.81
Requires-Dist: numpy>=1.21.0
Requires-Dist: matplotlib>=3.5.0
Requires-Dist: edlib>=1.3.9
Requires-Dist: kneed>=0.8.1
Requires-Dist: click>=8.1.0
